[{"name":"date","year":"2019","value":"16.04.2021"},{"name":"date","year":"2020","value":"16.04.2021"},{"name":"date","year":"2021","value":"15.04.2022"},{"name":"date","year":"2022","value":"11.04.2023"},{"name":"date","year":"2023","value":""},{"name":"currency","year":"2019","value":"RUB"},{"name":"currency","year":"2020","value":"RUB"},{"name":"currency","year":"2021","value":"RUB"},{"name":"currency","year":"2022","value":"RUB"},{"name":"currency","year":"2023","value":"RUB"},{"name":"report_url","year":"2019","value":"https://e-disclosure.ru/portal/FileLoad.ashx?Fileid=1628447"},{"name":"report_url","year":"2020","value":"https://e-disclosure.ru/portal/FileLoad.ashx?Fileid=1695606"},{"name":"report_url","year":"2021","value":"https://www.e-disclosure.ru/portal/FileLoad.ashx?Fileid=1745173"},{"name":"report_url","year":"2022","value":"https://invest.gemabank.ru/download/accounting-reports/MMCB_IFRS22.pdf"},{"name":"report_url","year":"2023","value":""},{"name":"year_report_url","year":"2019","value":"https://e-disclosure.ru/portal/FileLoad.ashx?Fileid=1643465"},{"name":"year_report_url","year":"2020","value":"https://e-disclosure.ru/portal/FileLoad.ashx?Fileid=1705113"},{"name":"year_report_url","year":"2021","value":"https://www.e-disclosure.ru/portal/FileLoad.ashx?Fileid=1755133"},{"name":"year_report_url","year":"2022","value":"https://www.e-disclosure.ru/portal/FileLoad.ashx?Fileid=1800437"},{"name":"year_report_url","year":"2023","value":""},{"name":"revenue","year":"2019","value":"0.239"},{"name":"revenue","year":"2020","value":"0.243"},{"name":"revenue","year":"2021","value":"0.266"},{"name":"revenue","year":"2022","value":"0.255"},{"name":"revenue","year":"2023","value":""},{"name":"operating_income","year":"2019","value":"0.137"},{"name":"operating_income","year":"2020","value":"0.142"},{"name":"operating_income","year":"2021","value":"0.140"},{"name":"operating_income","year":"2022","value":"0.139"},{"name":"operating_income","year":"2023","value":""},{"name":"ebitda","year":"2019","value":"0.142"},{"name":"ebitda","year":"2020","value":"0.152"},{"name":"ebitda","year":"2021","value":"0.148"},{"name":"ebitda","year":"2022","value":"0.145"},{"name":"ebitda","year":"2023","value":""},{"name":"net_income","year":"2019","value":"0.119"},{"name":"net_income","year":"2020","value":"0.123"},{"name":"net_income","year":"2021","value":"0.137"},{"name":"net_income","year":"2022","value":"0.113"},{"name":"net_income","year":"2023","value":""},{"name":"ocf","year":"2019","value":"0.113"},{"name":"ocf","year":"2020","value":"0.135"},{"name":"ocf","year":"2021","value":"0.243"},{"name":"ocf","year":"2022","value":"0.245"},{"name":"ocf","year":"2023","value":""},{"name":"capex","year":"2019","value":"0.000"},{"name":"capex","year":"2020","value":"0.002"},{"name":"capex","year":"2021","value":"0.005"},{"name":"capex","year":"2022","value":"0.004"},{"name":"capex","year":"2023","value":""},{"name":"fcf","year":"2019","value":"0.108"},{"name":"fcf","year":"2020","value":"0.129"},{"name":"fcf","year":"2021","value":"0.265"},{"name":"fcf","year":"2022","value":"0.243"},{"name":"fcf","year":"2023","value":""},{"name":"dividend_payout","year":"2019","value":"0.134"},{"name":"dividend_payout","year":"2020","value":"0.124"},{"name":"dividend_payout","year":"2021","value":"0.129"},{"name":"dividend_payout","year":"2022","value":"0.120"},{"name":"dividend_payout","year":"2023","value":"0.096"},{"name":"dividend","year":"2019","value":"89.45"},{"name":"dividend","year":"2020","value":"83.1"},{"name":"dividend","year":"2021","value":"86.5"},{"name":"dividend","year":"2022","value":"80.22"},{"name":"dividend","year":"2023","value":"64.2"},{"name":"div_yield","year":"2019","value":"11.7%"},{"name":"div_yield","year":"2020","value":"12.0%"},{"name":"div_yield","year":"2021","value":"8.7%"},{"name":"div_yield","year":"2022","value":"10.0%"},{"name":"div_yield","year":"2023","value":"6.4%"},{"name":"div_payout_ratio","year":"2019","value":"112%"},{"name":"div_payout_ratio","year":"2020","value":"101%"},{"name":"div_payout_ratio","year":"2021","value":"94%"},{"name":"div_payout_ratio","year":"2022","value":"106%"},{"name":"div_payout_ratio","year":"2023","value":""},{"name":"opex","year":"2019","value":"0.101"},{"name":"opex","year":"2020","value":"0.101"},{"name":"opex","year":"2021","value":"0.126"},{"name":"opex","year":"2022","value":"0.115"},{"name":"opex","year":"2023","value":""},{"name":"employment_expenses","year":"2019","value":"0.025"},{"name":"employment_expenses","year":"2020","value":"0.026"},{"name":"employment_expenses","year":"2021","value":"0.026"},{"name":"employment_expenses","year":"2022","value":"0.026"},{"name":"employment_expenses","year":"2023","value":""},{"name":"interest_expenses","year":"2019","value":"0.005"},{"name":"interest_expenses","year":"2020","value":"0.004"},{"name":"interest_expenses","year":"2021","value":"0.006"},{"name":"interest_expenses","year":"2022","value":"0.004"},{"name":"interest_expenses","year":"2023","value":""},{"name":"assets","year":"2019","value":"0.564"},{"name":"assets","year":"2020","value":"0.653"},{"name":"assets","year":"2021","value":"0.679"},{"name":"assets","year":"2022","value":"0.870"},{"name":"assets","year":"2023","value":""},{"name":"net_assets","year":"2019","value":"0.196"},{"name":"net_assets","year":"2020","value":"0.210"},{"name":"net_assets","year":"2021","value":"0.202"},{"name":"net_assets","year":"2022","value":"0.139"},{"name":"net_assets","year":"2023","value":""},{"name":"debt","year":"2019","value":"0.000"},{"name":"debt","year":"2020","value":"0.000"},{"name":"debt","year":"2021","value":"0.030"},{"name":"debt","year":"2022","value":"0.225"},{"name":"debt","year":"2023","value":""},{"name":"cash","year":"2019","value":"0.035"},{"name":"cash","year":"2020","value":"0.025"},{"name":"cash","year":"2021","value":"0.036"},{"name":"cash","year":"2022","value":"0.076"},{"name":"cash","year":"2023","value":""},{"name":"net_debt","year":"2019","value":"-0.04"},{"name":"net_debt","year":"2020","value":"-0.03"},{"name":"net_debt","year":"2021","value":"-0.01"},{"name":"net_debt","year":"2022","value":"0.15"},{"name":"net_debt","year":"2023","value":"0.00"},{"name":"common_share","year":"2019","value":"761.5"},{"name":"common_share","year":"2020","value":"690.0"},{"name":"common_share","year":"2021","value":"999.0"},{"name":"common_share","year":"2022","value":"799.5"},{"name":"common_share","year":"2023","value":"1 002"},{"name":"number_of_shares","year":"2019","value":"1.49"},{"name":"number_of_shares","year":"2020","value":"1.49"},{"name":"number_of_shares","year":"2021","value":"1.49"},{"name":"number_of_shares","year":"2022","value":"1.49"},{"name":"number_of_shares","year":"2023","value":"1.49"},{"name":"free_float","year":"2019","value":""},{"name":"free_float","year":"2020","value":""},{"name":"free_float","year":"2021","value":""},{"name":"free_float","year":"2022","value":""},{"name":"free_float","year":"2023","value":"13.0%"},{"name":"market_cap","year":"2019","value":"1.14"},{"name":"market_cap","year":"2020","value":"1.03"},{"name":"market_cap","year":"2021","value":"1.49"},{"name":"market_cap","year":"2022","value":"1.19"},{"name":"market_cap","year":"2023","value":"1.50"},{"name":"ev","year":"2019","value":"1.10"},{"name":"ev","year":"2020","value":"1.01"},{"name":"ev","year":"2021","value":"1.49"},{"name":"ev","year":"2022","value":"1.34"},{"name":"ev","year":"2023","value":"1.50"},{"name":"book_value","year":"2019","value":"0.16"},{"name":"book_value","year":"2020","value":"0.18"},{"name":"book_value","year":"2021","value":"0.18"},{"name":"book_value","year":"2022","value":"0.05"},{"name":"book_value","year":"2023","value":"0.00"},{"name":"eps","year":"2019","value":"79.7"},{"name":"eps","year":"2020","value":"82.4"},{"name":"eps","year":"2021","value":"91.8"},{"name":"eps","year":"2022","value":"75.7"},{"name":"eps","year":"2023","value":"0.00"},{"name":"fcf_share","year":"2019","value":"72.3"},{"name":"fcf_share","year":"2020","value":"86.4"},{"name":"fcf_share","year":"2021","value":"177.5"},{"name":"fcf_share","year":"2022","value":"162.8"},{"name":"fcf_share","year":"2023","value":"0.00"},{"name":"bv_share","year":"2019","value":"108.5"},{"name":"bv_share","year":"2020","value":"118.6"},{"name":"bv_share","year":"2021","value":"117.2"},{"name":"bv_share","year":"2022","value":"32.8"},{"name":"bv_share","year":"2023","value":"0.00"},{"name":"ebitda_margin","year":"2019","value":"59.4%"},{"name":"ebitda_margin","year":"2020","value":"62.6%"},{"name":"ebitda_margin","year":"2021","value":"55.6%"},{"name":"ebitda_margin","year":"2022","value":"56.9%"},{"name":"ebitda_margin","year":"2023","value":""},{"name":"net_margin","year":"2019","value":"49.8%"},{"name":"net_margin","year":"2020","value":"50.6%"},{"name":"net_margin","year":"2021","value":"51.5%"},{"name":"net_margin","year":"2022","value":"44.3%"},{"name":"net_margin","year":"2023","value":""},{"name":"fcf_yield","year":"2019","value":"9.5%"},{"name":"fcf_yield","year":"2020","value":"12.5%"},{"name":"fcf_yield","year":"2021","value":"17.8%"},{"name":"fcf_yield","year":"2022","value":"20.4%"},{"name":"fcf_yield","year":"2023","value":"0.0%"},{"name":"roe","year":"2019","value":"60.7%"},{"name":"roe","year":"2020","value":"58.6%"},{"name":"roe","year":"2021","value":"67.8%"},{"name":"roe","year":"2022","value":"81.3%"},{"name":"roe","year":"2023","value":""},{"name":"roa","year":"2019","value":"21.1%"},{"name":"roa","year":"2020","value":"18.8%"},{"name":"roa","year":"2021","value":"20.2%"},{"name":"roa","year":"2022","value":"13.0%"},{"name":"roa","year":"2023","value":""},{"name":"p_e","year":"2019","value":"9.55"},{"name":"p_e","year":"2020","value":"8.38"},{"name":"p_e","year":"2021","value":"10.9"},{"name":"p_e","year":"2022","value":"10.6"},{"name":"p_e","year":"2023","value":""},{"name":"p_fcf","year":"2019","value":"10.5"},{"name":"p_fcf","year":"2020","value":"7.99"},{"name":"p_fcf","year":"2021","value":"5.63"},{"name":"p_fcf","year":"2022","value":"4.91"},{"name":"p_fcf","year":"2023","value":""},{"name":"p_s","year":"2019","value":"4.76"},{"name":"p_s","year":"2020","value":"4.24"},{"name":"p_s","year":"2021","value":"5.61"},{"name":"p_s","year":"2022","value":"4.68"},{"name":"p_s","year":"2023","value":""},{"name":"p_bv","year":"2019","value":"7.02"},{"name":"p_bv","year":"2020","value":"5.82"},{"name":"p_bv","year":"2021","value":"8.52"},{"name":"p_bv","year":"2022","value":"24.4"},{"name":"p_bv","year":"2023","value":""},{"name":"ev_ebitda","year":"2019","value":"7.76"},{"name":"ev_ebitda","year":"2020","value":"6.61"},{"name":"ev_ebitda","year":"2021","value":"10.0"},{"name":"ev_ebitda","year":"2022","value":"9.26"},{"name":"ev_ebitda","year":"2023","value":""},{"name":"debt_ebitda","year":"2019","value":"-0.25"},{"name":"debt_ebitda","year":"2020","value":"-0.16"},{"name":"debt_ebitda","year":"2021","value":"-0.04"},{"name":"debt_ebitda","year":"2022","value":"1.03"},{"name":"debt_ebitda","year":"2023","value":""},{"name":"r_and_d_capex","year":"2019","value":""},{"name":"r_and_d_capex","year":"2020","value":"0.00%"},{"name":"r_and_d_capex","year":"2021","value":"0.00%"},{"name":"r_and_d_capex","year":"2022","value":"0.00%"},{"name":"r_and_d_capex","year":"2023","value":""},{"name":"capex_revenue","year":"2019","value":"0%"},{"name":"capex_revenue","year":"2020","value":"1%"},{"name":"capex_revenue","year":"2021","value":"2%"},{"name":"capex_revenue","year":"2022","value":"2%"},{"name":"capex_revenue","year":"2023","value":""}]