[{"name":"date","year":"2019","value":"21.04.2021"},{"name":"date","year":"2020","value":"21.04.2021"},{"name":"date","year":"2021","value":"28.02.2022"},{"name":"date","year":"2022","value":"21.03.2023"},{"name":"date","year":"2023","value":"01.04.2024"},{"name":"date","year":"LTM\n?","value":"15.07.2024"},{"name":"currency","year":"2019","value":"RUB"},{"name":"currency","year":"2020","value":"RUB"},{"name":"currency","year":"2021","value":"RUB"},{"name":"currency","year":"2022","value":"RUB"},{"name":"currency","year":"2023","value":"RUB"},{"name":"currency","year":"LTM\n?","value":"RUB"},{"name":"report_url","year":"2019","value":"https://e-disclosure.ru/portal/FileLoad.ashx?Fileid=1614326"},{"name":"report_url","year":"2020","value":"https://e-disclosure.ru/portal/FileLoad.ashx?Fileid=1680327"},{"name":"report_url","year":"2021","value":"https://www.e-disclosure.ru/portal/FileLoad.ashx?Fileid=1736636"},{"name":"report_url","year":"2022","value":"https://www.e-disclosure.ru/portal/FileLoad.ashx?Fileid=1782468"},{"name":"report_url","year":"2023","value":"https://www.e-disclosure.ru/portal/FileLoad.ashx?Fileid=1828811"},{"name":"report_url","year":"LTM\n?","value":"https://www.e-disclosure.ru/portal/FileLoad.ashx?Fileid=1847851"},{"name":"year_report_url","year":"2019","value":"https://e-disclosure.ru/portal/FileLoad.ashx?Fileid=1638205"},{"name":"year_report_url","year":"2020","value":"https://e-disclosure.ru/portal/FileLoad.ashx?Fileid=1704914"},{"name":"year_report_url","year":"2021","value":""},{"name":"year_report_url","year":"2022","value":""},{"name":"year_report_url","year":"2023","value":""},{"name":"year_report_url","year":"LTM\n?","value":""},{"name":"revenue","year":"2019","value":"0.198"},{"name":"revenue","year":"2020","value":"0.096"},{"name":"revenue","year":"2021","value":"0.123"},{"name":"revenue","year":"2022","value":"0.066"},{"name":"revenue","year":"2023","value":"0.300"},{"name":"revenue","year":"LTM\n?","value":"0.379"},{"name":"operating_income","year":"2019","value":"-0.071"},{"name":"operating_income","year":"2020","value":"-0.105"},{"name":"operating_income","year":"2021","value":"-0.160"},{"name":"operating_income","year":"2022","value":"-0.119"},{"name":"operating_income","year":"2023","value":"-0.101"},{"name":"operating_income","year":"LTM\n?","value":"-0.164"},{"name":"net_income","year":"2019","value":"0.142"},{"name":"net_income","year":"2020","value":"0.249"},{"name":"net_income","year":"2021","value":"0.025"},{"name":"net_income","year":"2022","value":"0.344"},{"name":"net_income","year":"2023","value":"-0.468"},{"name":"net_income","year":"LTM\n?","value":"-0.492"},{"name":"ocf","year":"2019","value":"-0.165"},{"name":"ocf","year":"2020","value":"-0.217"},{"name":"ocf","year":"2021","value":"-0.160"},{"name":"ocf","year":"2022","value":"-0.316"},{"name":"ocf","year":"2023","value":"-0.244"},{"name":"ocf","year":"LTM\n?","value":""},{"name":"capex","year":"2019","value":"0.009"},{"name":"capex","year":"2020","value":"0.001"},{"name":"capex","year":"2021","value":"0.002"},{"name":"capex","year":"2022","value":"0.085"},{"name":"capex","year":"2023","value":"0.340"},{"name":"capex","year":"LTM\n?","value":""},{"name":"fcf","year":"2019","value":"-0.174"},{"name":"fcf","year":"2020","value":"-0.218"},{"name":"fcf","year":"2021","value":"-0.018"},{"name":"fcf","year":"2022","value":"-0.400"},{"name":"fcf","year":"2023","value":"-0.584"},{"name":"fcf","year":"LTM\n?","value":""},{"name":"div_yield","year":"2019","value":"0.0%"},{"name":"div_yield","year":"2020","value":"0.0%"},{"name":"div_yield","year":"2021","value":"0.0%"},{"name":"div_yield","year":"2022","value":"0.0%"},{"name":"div_yield","year":"2023","value":"0.0%"},{"name":"div_yield","year":"LTM\n?","value":"0"},{"name":"div_payout_ratio","year":"2019","value":"0%"},{"name":"div_payout_ratio","year":"2020","value":"0%"},{"name":"div_payout_ratio","year":"2021","value":"0%"},{"name":"div_payout_ratio","year":"2022","value":"0%"},{"name":"div_payout_ratio","year":"2023","value":"0%"},{"name":"div_payout_ratio","year":"LTM\n?","value":"0"},{"name":"cost_of_production","year":"2019","value":"0.095"},{"name":"cost_of_production","year":"2020","value":"0.054"},{"name":"cost_of_production","year":"2021","value":"0.071"},{"name":"cost_of_production","year":"2022","value":"0.066"},{"name":"cost_of_production","year":"2023","value":"0.256"},{"name":"cost_of_production","year":"LTM\n?","value":"0.376"},{"name":"assets","year":"2019","value":"8.49"},{"name":"assets","year":"2020","value":"8.76"},{"name":"assets","year":"2021","value":"10.5"},{"name":"assets","year":"2022","value":"9.82"},{"name":"assets","year":"2023","value":"9.14"},{"name":"assets","year":"LTM\n?","value":"9.07"},{"name":"net_assets","year":"2019","value":"8.13"},{"name":"net_assets","year":"2020","value":"8.38"},{"name":"net_assets","year":"2021","value":"8.40"},{"name":"net_assets","year":"2022","value":"8.75"},{"name":"net_assets","year":"2023","value":"8.28"},{"name":"net_assets","year":"LTM\n?","value":"8.22"},{"name":"net_debt","year":"2019","value":"0.00"},{"name":"net_debt","year":"2020","value":"0.00"},{"name":"net_debt","year":"2021","value":"0.00"},{"name":"net_debt","year":"2022","value":"0.00"},{"name":"net_debt","year":"2023","value":"0.00"},{"name":"net_debt","year":"LTM\n?","value":"0"},{"name":"common_share","year":"2019","value":"2 990"},{"name":"common_share","year":"2020","value":"7 650"},{"name":"common_share","year":"2021","value":"8 160"},{"name":"common_share","year":"2022","value":"7 210"},{"name":"common_share","year":"2023","value":"7 680"},{"name":"common_share","year":"LTM\n?","value":"4 880"},{"name":"number_of_shares","year":"2019","value":"0.600"},{"name":"number_of_shares","year":"2020","value":"0.600"},{"name":"number_of_shares","year":"2021","value":"0.600"},{"name":"number_of_shares","year":"2022","value":"0.600"},{"name":"number_of_shares","year":"2023","value":"0.600"},{"name":"number_of_shares","year":"LTM\n?","value":"0.600"},{"name":"market_cap","year":"2019","value":"1.79"},{"name":"market_cap","year":"2020","value":"4.59"},{"name":"market_cap","year":"2021","value":"4.89"},{"name":"market_cap","year":"2022","value":"4.32"},{"name":"market_cap","year":"2023","value":"4.61"},{"name":"market_cap","year":"LTM\n?","value":"2.93"},{"name":"ev","year":"2019","value":"1.79"},{"name":"ev","year":"2020","value":"4.59"},{"name":"ev","year":"2021","value":"4.89"},{"name":"ev","year":"2022","value":"4.32"},{"name":"ev","year":"2023","value":"4.61"},{"name":"ev","year":"LTM\n?","value":"2.93"},{"name":"book_value","year":"2019","value":"8.13"},{"name":"book_value","year":"2020","value":"8.38"},{"name":"book_value","year":"2021","value":"8.40"},{"name":"book_value","year":"2022","value":"8.75"},{"name":"book_value","year":"2023","value":"8.28"},{"name":"book_value","year":"LTM\n?","value":"8.22"},{"name":"eps","year":"2019","value":"236.8"},{"name":"eps","year":"2020","value":"415.2"},{"name":"eps","year":"2021","value":"41.7"},{"name":"eps","year":"2022","value":"573.6"},{"name":"eps","year":"2023","value":"-780.3"},{"name":"eps","year":"LTM\n?","value":"-820.4"},{"name":"fcf_share","year":"2019","value":"-290.1"},{"name":"fcf_share","year":"2020","value":"-363.5"},{"name":"fcf_share","year":"2021","value":"-30.0"},{"name":"fcf_share","year":"2022","value":"-667.0"},{"name":"fcf_share","year":"2023","value":"-973.8"},{"name":"fcf_share","year":"LTM\n?","value":"0"},{"name":"bv_share","year":"2019","value":"13 558"},{"name":"bv_share","year":"2020","value":"13 973"},{"name":"bv_share","year":"2021","value":"14 013"},{"name":"bv_share","year":"2022","value":"14 590"},{"name":"bv_share","year":"2023","value":"13 806"},{"name":"bv_share","year":"LTM\n?","value":"13 706"},{"name":"ebitda_margin","year":"2019","value":"0.0%"},{"name":"ebitda_margin","year":"2020","value":"0.0%"},{"name":"ebitda_margin","year":"2021","value":"0.0%"},{"name":"ebitda_margin","year":"2022","value":"0.0%"},{"name":"ebitda_margin","year":"2023","value":"0.0%"},{"name":"ebitda_margin","year":"LTM\n?","value":"0"},{"name":"net_margin","year":"2019","value":"71.7%"},{"name":"net_margin","year":"2020","value":"259.4%"},{"name":"net_margin","year":"2021","value":"20.3%"},{"name":"net_margin","year":"2022","value":"521.2%"},{"name":"net_margin","year":"2023","value":"-156.0%"},{"name":"net_margin","year":"LTM\n?","value":"-129.8%"},{"name":"fcf_yield","year":"2019","value":"-9.7%"},{"name":"fcf_yield","year":"2020","value":"-4.8%"},{"name":"fcf_yield","year":"2021","value":"-0.4%"},{"name":"fcf_yield","year":"2022","value":"-9.3%"},{"name":"fcf_yield","year":"2023","value":"-12.7%"},{"name":"fcf_yield","year":"LTM\n?","value":"0"},{"name":"roe","year":"2019","value":"1.7%"},{"name":"roe","year":"2020","value":"3.0%"},{"name":"roe","year":"2021","value":"0.3%"},{"name":"roe","year":"2022","value":"3.9%"},{"name":"roe","year":"2023","value":"-5.7%"},{"name":"roe","year":"LTM\n?","value":"-6.0%"},{"name":"roa","year":"2019","value":"1.7%"},{"name":"roa","year":"2020","value":"2.8%"},{"name":"roa","year":"2021","value":"0.2%"},{"name":"roa","year":"2022","value":"3.5%"},{"name":"roa","year":"2023","value":"-5.1%"},{"name":"roa","year":"LTM\n?","value":"-5.4%"},{"name":"p_e","year":"2019","value":"12.6"},{"name":"p_e","year":"2020","value":"18.4"},{"name":"p_e","year":"2021","value":"195.8"},{"name":"p_e","year":"2022","value":"12.6"},{"name":"p_e","year":"2023","value":"-9.84"},{"name":"p_e","year":"LTM\n?","value":"-5.95"},{"name":"p_fcf","year":"2019","value":"-10.3"},{"name":"p_fcf","year":"2020","value":"-21.0"},{"name":"p_fcf","year":"2021","value":"-271.9"},{"name":"p_fcf","year":"2022","value":"-10.8"},{"name":"p_fcf","year":"2023","value":"-7.89"},{"name":"p_fcf","year":"LTM\n?","value":""},{"name":"p_s","year":"2019","value":"9.06"},{"name":"p_s","year":"2020","value":"47.8"},{"name":"p_s","year":"2021","value":"39.8"},{"name":"p_s","year":"2022","value":"65.5"},{"name":"p_s","year":"2023","value":"15.4"},{"name":"p_s","year":"LTM\n?","value":"7.72"},{"name":"p_bv","year":"2019","value":"0.22"},{"name":"p_bv","year":"2020","value":"0.55"},{"name":"p_bv","year":"2021","value":"0.58"},{"name":"p_bv","year":"2022","value":"0.49"},{"name":"p_bv","year":"2023","value":"0.56"},{"name":"p_bv","year":"LTM\n?","value":"0.36"},{"name":"r_and_d_capex","year":"2019","value":"0.00%"},{"name":"r_and_d_capex","year":"2020","value":"0.00%"},{"name":"r_and_d_capex","year":"2021","value":"0.00%"},{"name":"r_and_d_capex","year":"2022","value":"0.00%"},{"name":"r_and_d_capex","year":"2023","value":"0.00%"},{"name":"r_and_d_capex","year":"LTM\n?","value":""},{"name":"capex_revenue","year":"2019","value":"5%"},{"name":"capex_revenue","year":"2020","value":"1%"},{"name":"capex_revenue","year":"2021","value":"2%"},{"name":"capex_revenue","year":"2022","value":"129%"},{"name":"capex_revenue","year":"2023","value":"113%"},{"name":"capex_revenue","year":"LTM\n?","value":"0"}]