[{"name":"Выручка","year":"2023","value":"17486543000"},{"name":"Выручка","year":"2022","value":"16372087000"},{"name":"Выручка","year":"2021","value":"14979972000"},{"name":"Выручка","year":"2020","value":"14551838000"},{"name":"Выручка","year":"2019","value":"14846295000"},{"name":"Валовая прибыль","year":"2023","value":"7206337000"},{"name":"Валовая прибыль","year":"2022","value":"7343440000"},{"name":"Валовая прибыль","year":"2021","value":"3790139000"},{"name":"Валовая прибыль","year":"2020","value":"4450022000"},{"name":"Валовая прибыль","year":"2019","value":"4397523000"},{"name":"EBITDA","year":"2023","value":"4561957000"},{"name":"EBITDA","year":"2022","value":"4865546000"},{"name":"EBITDA","year":"2021","value":"2059183000"},{"name":"EBITDA","year":"2020","value":"2262292000"},{"name":"EBITDA","year":"2019","value":"2495074000"},{"name":"EBIT","year":"2023","value":"3891282000"},{"name":"EBIT","year":"2022","value":"4325531000"},{"name":"EBIT","year":"2021","value":"1402259000"},{"name":"EBIT","year":"2020","value":"1628748000"},{"name":"EBIT","year":"2019","value":"2003780000"},{"name":"Процентные доходы","year":"2023","value":"181626000"},{"name":"Процентные доходы","year":"2022","value":"106010000"},{"name":"Процентные доходы","year":"2021","value":"35886000"},{"name":"Процентные доходы","year":"2020","value":"18993000"},{"name":"Процентные доходы","year":"2019","value":"24552000"},{"name":"Процентные расходы","year":"2023","value":"365478000"},{"name":"Процентные расходы","year":"2022","value":"699203000"},{"name":"Процентные расходы","year":"2021","value":"432591000"},{"name":"Процентные расходы","year":"2020","value":"461289000"},{"name":"Процентные расходы","year":"2019","value":"513482000"},{"name":"Чистые процентные доходы/расходы","year":"2023","value":"-183852000"},{"name":"Чистые процентные доходы/расходы","year":"2022","value":"-593193000"},{"name":"Чистые процентные доходы/расходы","year":"2021","value":"-396705000"},{"name":"Чистые процентные доходы/расходы","year":"2020","value":"-442296000"},{"name":"Чистые процентные доходы/расходы","year":"2019","value":"-488930000"},{"name":"Операционный доход","year":"2023","value":"3891282000"},{"name":"Операционный доход","year":"2022","value":"4325531000"},{"name":"Операционный доход","year":"2021","value":"1402259000"},{"name":"Операционный доход","year":"2020","value":"1628748000"},{"name":"Операционный доход","year":"2019","value":"2003780000"},{"name":"Расходы на персонал","year":"2023","value":"3148091000"},{"name":"Расходы на персонал","year":"2022","value":"2325052000"},{"name":"Расходы на персонал","year":"2021","value":"2205525000"},{"name":"Расходы на персонал","year":"2020","value":"2179403000"},{"name":"Расходы на персонал","year":"2019","value":"2095654000"},{"name":"Прибыль до налогов","year":"2023","value":"3707430000"},{"name":"Прибыль до налогов","year":"2022","value":"3732338000"},{"name":"Прибыль до налогов","year":"2021","value":"1005554000"},{"name":"Прибыль до налогов","year":"2020","value":"1186452000"},{"name":"Прибыль до налогов","year":"2019","value":"1514850000"},{"name":"Чистая прибыль","year":"2023","value":"2900750000"},{"name":"Чистая прибыль","year":"2022","value":"3008152000"},{"name":"Чистая прибыль","year":"2021","value":"761555000"},{"name":"Чистая прибыль","year":"2020","value":"896515000"},{"name":"Чистая прибыль","year":"2019","value":"1095591000"},{"name":"Капитал на акционеров","year":"2023","value":"11348733000"},{"name":"Капитал на акционеров","year":"2022","value":"8323705000"},{"name":"Капитал на акционеров","year":"2021","value":"5398205000"},{"name":"Капитал на акционеров","year":"2020","value":"4720784000"},{"name":"Капитал на акционеров","year":"2019","value":"3453881000"},{"name":"Активы","year":"2023","value":"17909078000"},{"name":"Активы","year":"2022","value":"15353203000"},{"name":"Активы","year":"2021","value":"14020521000"},{"name":"Активы","year":"2020","value":"12750007000"},{"name":"Активы","year":"2019","value":"11241518000"},{"name":"CA Оборотные активы","year":"2023","value":"6183793000"},{"name":"CA Оборотные активы","year":"2022","value":"7881275000"},{"name":"CA Оборотные активы","year":"2021","value":"6153421000"},{"name":"CA Оборотные активы","year":"2020","value":"5033846000"},{"name":"CA Оборотные активы","year":"2019","value":"4259847000"},{"name":"Денежные средства и их эквиваленты","year":"2023","value":"198645000"},{"name":"Денежные средства и их эквиваленты","year":"2022","value":"388313000"},{"name":"Денежные средства и их эквиваленты","year":"2021","value":"181824000"},{"name":"Денежные средства и их эквиваленты","year":"2020","value":"534425000"},{"name":"Денежные средства и их эквиваленты","year":"2019","value":"11606000"},{"name":"Обязательства","year":"2023","value":"6560345000"},{"name":"Обязательства","year":"2022","value":"7029498000"},{"name":"Обязательства","year":"2021","value":"8622317000"},{"name":"Обязательства","year":"2020","value":"8029224000"},{"name":"Обязательства","year":"2019","value":"7304766000"},{"name":"Собственный капитал","year":"2023","value":"11348733000"},{"name":"Собственный капитал","year":"2022","value":"8323705000"},{"name":"Собственный капитал","year":"2021","value":"5398205000"},{"name":"Собственный капитал","year":"2020","value":"4720784000"},{"name":"Собственный капитал","year":"2019","value":"3936754000"},{"name":"Капитал на акционеров","year":"2023","value":"2900750000"},{"name":"Капитал на акционеров","year":"2022","value":"3008152000"},{"name":"Капитал на акционеров","year":"2021","value":"761555000"},{"name":"Капитал на акционеров","year":"2020","value":"896515000"},{"name":"Капитал на акционеров","year":"2019","value":"919385000"},{"name":"Внеоборотные активы","year":"2023","value":"11725285000"},{"name":"Внеоборотные активы","year":"2022","value":"7471928000"},{"name":"Внеоборотные активы","year":"2021","value":"7867100000"},{"name":"Внеоборотные активы","year":"2020","value":"7716161000"},{"name":"Внеоборотные активы","year":"2019","value":"6981671000"},{"name":"Собственный капитал","year":"2023","value":"83.6492"},{"name":"Собственный капитал","year":"2022","value":"37.5704"},{"name":"Собственный капитал","year":"2021","value":"38.386"},{"name":"Собственный капитал","year":"2020","value":"32.8517"},{"name":"Собственный капитал","year":"2019","value":"33.4803"},{"name":"CFO операционные денежные потоки","year":"2023","value":"3735565000"},{"name":"CFO операционные денежные потоки","year":"2022","value":"3905603000"},{"name":"CFO операционные денежные потоки","year":"2021","value":"77549000"},{"name":"CFO операционные денежные потоки","year":"2020","value":"1537380000"},{"name":"CFO операционные денежные потоки","year":"2019","value":"1404078000"},{"name":"FCF на акцию","year":"2023","value":"1381950000"},{"name":"FCF на акцию","year":"2022","value":"3037031000"},{"name":"FCF на акцию","year":"2021","value":"-422324000"},{"name":"FCF на акцию","year":"2020","value":"829163000"},{"name":"FCF на акцию","year":"2019","value":"804367000"},{"name":"Инвестиционный денежный поток","year":"2023","value":"-2971044000"},{"name":"Инвестиционный денежный поток","year":"2022","value":"-1409388000"},{"name":"Инвестиционный денежный поток","year":"2021","value":"-1002522000"},{"name":"Инвестиционный денежный поток","year":"2020","value":"-715852000"},{"name":"Инвестиционный денежный поток","year":"2019","value":"-626287000"},{"name":"CFF Денежный поток от финансовой деятельности","year":"2023","value":"-954189000"},{"name":"CFF Денежный поток от финансовой деятельности","year":"2022","value":"-2289726000"},{"name":"CFF Денежный поток от финансовой деятельности","year":"2021","value":"572371000"},{"name":"CFF Денежный поток от финансовой деятельности","year":"2020","value":"-298709000"},{"name":"CFF Денежный поток от финансовой деятельности","year":"2019","value":"-845464000"},{"name":"CB Текущие кредиты","year":"2023","value":"1311677000"},{"name":"CB Текущие кредиты","year":"2022","value":"2226377000"},{"name":"CB Текущие кредиты","year":"2021","value":"3267450000"},{"name":"CB Текущие кредиты","year":"2020","value":"3134117000"},{"name":"CB Текущие кредиты","year":"2019","value":"3169897000"},{"name":"Общий долг","year":"2023","value":"2522532000"},{"name":"Общий долг","year":"2022","value":"3100564000"},{"name":"Общий долг","year":"2021","value":"5408693000"},{"name":"Общий долг","year":"2020","value":"4400156000"},{"name":"Общий долг","year":"2019","value":"5018148000"},{"name":"Текущие обязательства","year":"2023","value":"3875198000"},{"name":"Текущие обязательства","year":"2022","value":"5261972000"},{"name":"Текущие обязательства","year":"2021","value":"5969262000"},{"name":"Текущие обязательства","year":"2020","value":"5558546000"},{"name":"Текущие обязательства","year":"2019","value":"5097255000"},{"name":"CL Текущая аренда","year":"2023","value":"141477000"},{"name":"CL Текущая аренда","year":"2022","value":"104563000"},{"name":"CL Текущая аренда","year":"2021","value":"122228000"},{"name":"CL Текущая аренда","year":"2020","value":"225104000"},{"name":"CL Текущая аренда","year":"2019","value":"185108000"},{"name":"Долгосрочная аренда","year":"2023","value":"623470000"},{"name":"Долгосрочная аренда","year":"2022","value":"345163000"},{"name":"Долгосрочная аренда","year":"2021","value":"280148000"},{"name":"Долгосрочная аренда","year":"2020","value":"546073000"},{"name":"Долгосрочная аренда","year":"2019","value":"238160000"},{"name":"Долгосрочные кредиты","year":"2023","value":"1409500000"},{"name":"Долгосрочные кредиты","year":"2022","value":"1262500000"},{"name":"Долгосрочные кредиты","year":"2021","value":"2323067000"},{"name":"Долгосрочные кредиты","year":"2020","value":"1800464000"},{"name":"Долгосрочные кредиты","year":"2019","value":"1859857000"},{"name":"Долгосрочные обязательства","year":"2023","value":"2685147000"},{"name":"Долгосрочные обязательства","year":"2022","value":"1767526000"},{"name":"Долгосрочные обязательства","year":"2021","value":"2653055000"},{"name":"Долгосрочные обязательства","year":"2020","value":"2470678000"},{"name":"Долгосрочные обязательства","year":"2019","value":"2207511000"},{"name":"Чистый долг","year":"2023","value":"2721177000"},{"name":"Чистый долг","year":"2022","value":"3488877000"},{"name":"Чистый долг","year":"2021","value":"5590517000"},{"name":"Чистый долг","year":"2020","value":"4934581000"},{"name":"Чистый долг","year":"2019","value":"5029754000"},{"name":"Общие расходы","year":"2023","value":"3315055000"},{"name":"Общие расходы","year":"2022","value":"3017909000"},{"name":"Общие расходы","year":"2021","value":"2387880000"},{"name":"Общие расходы","year":"2020","value":"2821274000"},{"name":"Общие расходы","year":"2019","value":"2393743000"}]